{
	"name": "teamEvent_AT",
	"events": [
		{
			"eventType": "block",
			"conditions": [
				{
					"id": "on-start-of-layout",
					"objectClass": "System",
					"sid": 525473652976615
				}
			],
			"actions": [
				{
					"id": "set-cursor-style",
					"objectClass": "Mouse",
					"sid": 561245585194769,
					"parameters": {
						"cursor-style": "none"
					}
				},
				{
					"id": "set-position",
					"objectClass": "fadeIn2",
					"sid": 429790696596566,
					"parameters": {
						"x": "966",
						"y": "540"
					}
				},
				{
					"id": "tween-one-property",
					"objectClass": "fadeIn2",
					"sid": 642438908400563,
					"behaviorType": "Tween",
					"parameters": {
						"tags": "\"fadeIn2\"",
						"property": "offsetOpacity",
						"end-value": "0",
						"time": ".5",
						"ease": "default",
						"destroy-on-complete": "no",
						"loop": "no",
						"ping-pong": "no",
						"repeat-count": "1"
					}
				}
			],
			"sid": 989914673393117
		},
		{
			"eventType": "block",
			"conditions": [
				{
					"id": "every-tick",
					"objectClass": "System",
					"sid": 370832137251835
				}
			],
			"actions": [
				{
					"id": "set-position",
					"objectClass": "pointer",
					"sid": 292060537520702,
					"parameters": {
						"x": "Mouse.X",
						"y": "Mouse.Y"
					}
				}
			],
			"sid": 531116767146506
		},
		{
			"eventType": "block",
			"conditions": [
				{
					"id": "on-click",
					"objectClass": "Mouse",
					"sid": 437260084721268,
					"parameters": {
						"mouse-button": "left",
						"click-type": "clicked"
					}
				}
			],
			"actions": [
				{
					"id": "set-animation-frame",
					"objectClass": "pointer",
					"sid": 412214821348001,
					"parameters": {
						"frame-number": "1"
					}
				}
			],
			"sid": 996612853100440
		},
		{
			"eventType": "block",
			"conditions": [
				{
					"id": "on-button-released",
					"objectClass": "Mouse",
					"sid": 323237378624760,
					"parameters": {
						"mouse-button": "left"
					}
				}
			],
			"actions": [
				{
					"id": "set-animation-frame",
					"objectClass": "pointer",
					"sid": 233604915618082,
					"parameters": {
						"frame-number": "0"
					}
				}
			],
			"sid": 548108260153071
		},
		{
			"eventType": "block",
			"conditions": [
				{
					"id": "cursor-is-over-object",
					"objectClass": "Mouse",
					"sid": 891973541030464,
					"parameters": {
						"object": "back"
					},
					"isInverted": true
				}
			],
			"actions": [
				{
					"id": "set-effect-enabled",
					"objectClass": "back",
					"sid": 704510467995540,
					"parameters": {
						"mode": "disable",
						"effect": "\"GlowHorizontal\""
					}
				}
			],
			"sid": 868648633947427
		},
		{
			"eventType": "block",
			"conditions": [
				{
					"id": "cursor-is-over-object",
					"objectClass": "Mouse",
					"sid": 589324476145302,
					"parameters": {
						"object": "back"
					}
				}
			],
			"actions": [
				{
					"id": "set-effect-enabled",
					"objectClass": "back",
					"sid": 132941795999571,
					"parameters": {
						"mode": "enable",
						"effect": "\"GlowHorizontal\""
					}
				}
			],
			"sid": 731317635202436
		},
		{
			"eventType": "block",
			"conditions": [
				{
					"id": "on-click",
					"objectClass": "Mouse",
					"sid": 580405959495833,
					"parameters": {
						"mouse-button": "left",
						"click-type": "clicked"
					}
				},
				{
					"id": "cursor-is-over-object",
					"objectClass": "Mouse",
					"sid": 156145698199795,
					"parameters": {
						"object": "back"
					}
				}
			],
			"actions": [
				{
					"id": "set-effect-enabled",
					"objectClass": "back",
					"sid": 509330734501937,
					"parameters": {
						"mode": "enable",
						"effect": "\"GlowHorizontal\""
					}
				},
				{
					"id": "tween-one-property",
					"objectClass": "fadeIn2",
					"sid": 829861115783882,
					"behaviorType": "Tween",
					"parameters": {
						"tags": "\"fadeIn3\"",
						"property": "offsetOpacity",
						"end-value": "99",
						"time": ".5",
						"ease": "default",
						"destroy-on-complete": "no",
						"loop": "no",
						"ping-pong": "no",
						"repeat-count": "1"
					}
				},
				{
					"id": "wait",
					"objectClass": "System",
					"sid": 930790723585347,
					"parameters": {
						"seconds": "0.6"
					}
				},
				{
					"id": "go-to-layout",
					"objectClass": "System",
					"sid": 296390539936500,
					"parameters": {
						"layout": "mainLayout_AT"
					}
				}
			],
			"sid": 247768822268570
		},
		{
			"eventType": "block",
			"conditions": [
				{
					"id": "cursor-is-over-object",
					"objectClass": "Mouse",
					"sid": 170060097984135,
					"parameters": {
						"object": "anthony"
					}
				}
			],
			"actions": [
				{
					"id": "set-animation-frame",
					"objectClass": "anthony",
					"sid": 286603695309828,
					"parameters": {
						"frame-number": "1"
					}
				}
			],
			"sid": 964219892262764
		},
		{
			"eventType": "block",
			"conditions": [
				{
					"id": "cursor-is-over-object",
					"objectClass": "Mouse",
					"sid": 612103605433729,
					"parameters": {
						"object": "anthony"
					},
					"isInverted": true
				}
			],
			"actions": [
				{
					"id": "set-animation-frame",
					"objectClass": "anthony",
					"sid": 160854693741550,
					"parameters": {
						"frame-number": "0"
					}
				}
			],
			"sid": 953301006827845
		},
		{
			"eventType": "block",
			"conditions": [
				{
					"id": "cursor-is-over-object",
					"objectClass": "Mouse",
					"sid": 930907019502223,
					"parameters": {
						"object": "adam"
					}
				}
			],
			"actions": [
				{
					"id": "set-animation-frame",
					"objectClass": "adam",
					"sid": 847571872970576,
					"parameters": {
						"frame-number": "1"
					}
				}
			],
			"sid": 593724326786689
		},
		{
			"eventType": "block",
			"conditions": [
				{
					"id": "cursor-is-over-object",
					"objectClass": "Mouse",
					"sid": 927482634426730,
					"parameters": {
						"object": "adam"
					},
					"isInverted": true
				}
			],
			"actions": [
				{
					"id": "set-animation-frame",
					"objectClass": "adam",
					"sid": 398427601764660,
					"parameters": {
						"frame-number": "0"
					}
				}
			],
			"sid": 247500624360445
		},
		{
			"eventType": "block",
			"conditions": [
				{
					"id": "cursor-is-over-object",
					"objectClass": "Mouse",
					"sid": 815343156335442,
					"parameters": {
						"object": "tay"
					}
				}
			],
			"actions": [
				{
					"id": "set-animation-frame",
					"objectClass": "tay",
					"sid": 779403226496215,
					"parameters": {
						"frame-number": "1"
					}
				}
			],
			"sid": 885923188543195
		},
		{
			"eventType": "block",
			"conditions": [
				{
					"id": "cursor-is-over-object",
					"objectClass": "Mouse",
					"sid": 714486101663555,
					"parameters": {
						"object": "tay"
					},
					"isInverted": true
				}
			],
			"actions": [
				{
					"id": "set-animation-frame",
					"objectClass": "tay",
					"sid": 401509844820041,
					"parameters": {
						"frame-number": "0"
					}
				}
			],
			"sid": 366585013384815
		},
		{
			"eventType": "block",
			"conditions": [
				{
					"id": "cursor-is-over-object",
					"objectClass": "Mouse",
					"sid": 643563320535518,
					"parameters": {
						"object": "thomas"
					}
				}
			],
			"actions": [
				{
					"id": "set-animation-frame",
					"objectClass": "thomas",
					"sid": 365321296199197,
					"parameters": {
						"frame-number": "1"
					}
				}
			],
			"sid": 411185310202712
		},
		{
			"eventType": "block",
			"conditions": [
				{
					"id": "cursor-is-over-object",
					"objectClass": "Mouse",
					"sid": 431634507661023,
					"parameters": {
						"object": "thomas"
					},
					"isInverted": true
				}
			],
			"actions": [
				{
					"id": "set-animation-frame",
					"objectClass": "thomas",
					"sid": 601821101850152,
					"parameters": {
						"frame-number": "0"
					}
				}
			],
			"sid": 871561014801150
		},
		{
			"eventType": "block",
			"conditions": [
				{
					"id": "cursor-is-over-object",
					"objectClass": "Mouse",
					"sid": 348033432342841,
					"parameters": {
						"object": "isis"
					}
				}
			],
			"actions": [
				{
					"id": "set-animation-frame",
					"objectClass": "isis",
					"sid": 400949033265124,
					"parameters": {
						"frame-number": "1"
					}
				}
			],
			"sid": 216684913545001
		},
		{
			"eventType": "block",
			"conditions": [
				{
					"id": "cursor-is-over-object",
					"objectClass": "Mouse",
					"sid": 854005863273797,
					"parameters": {
						"object": "isis"
					},
					"isInverted": true
				}
			],
			"actions": [
				{
					"id": "set-animation-frame",
					"objectClass": "isis",
					"sid": 505427436233629,
					"parameters": {
						"frame-number": "0"
					}
				}
			],
			"sid": 297756055841947
		}
	],
	"sid": 228606722800562
}