{
	"name": "Sink",
	"plugin-id": "Sprite",
	"sid": 835486512369706,
	"isGlobal": false,
	"instanceVariables": [],
	"behaviorTypes": [],
	"effectTypes": [],
	"animations": {
		"items": [
			{
				"frames": [
					{
						"width": 120,
						"height": 120,
						"originX": 0.5,
						"originY": 0.5,
						"originalSource": "",
						"exportFormat": "lossless",
						"exportQuality": 1,
						"imageSpriteId": 9880928,
						"collisionPoly": {
							"points": [
								0.4166666666666667,
								0.31666666666666665,
								0.575,
								0.35,
								0.7416666666666667,
								1,
								0.21666666666666667,
								0.9666666666666667,
								0.38333333333333336,
								0.35
							]
						},
						"useCollisionPoly": true,
						"duration": 1,
						"tag": ""
					}
				],
				"sid": 952121787100519,
				"name": "Idle",
				"isLooping": false,
				"isPingPong": false,
				"repeatCount": 1,
				"repeatTo": 0,
				"speed": 5
			},
			{
				"frames": [
					{
						"width": 120,
						"height": 120,
						"originX": 0.5,
						"originY": 0.5,
						"originalSource": "",
						"exportFormat": "lossless",
						"exportQuality": 0.8,
						"imageSpriteId": 6097635,
						"collisionPoly": {
							"points": [
								0.4166666666666667,
								0.31666666666666665,
								0.575,
								0.35,
								0.7416666666666667,
								1,
								0.21666666666666667,
								0.9666666666666667,
								0.38333333333333336,
								0.35
							]
						},
						"useCollisionPoly": true,
						"duration": 1,
						"tag": ""
					},
					{
						"width": 120,
						"height": 120,
						"originX": 0.5,
						"originY": 0.5,
						"originalSource": "",
						"exportFormat": "lossless",
						"exportQuality": 0.8,
						"imageSpriteId": 3369785,
						"useCollisionPoly": true,
						"duration": 1,
						"tag": ""
					},
					{
						"width": 120,
						"height": 120,
						"originX": 0.5,
						"originY": 0.5,
						"originalSource": "",
						"exportFormat": "lossless",
						"exportQuality": 0.8,
						"imageSpriteId": 6834336,
						"useCollisionPoly": true,
						"duration": 1,
						"tag": ""
					},
					{
						"width": 120,
						"height": 120,
						"originX": 0.5,
						"originY": 0.5,
						"originalSource": "",
						"exportFormat": "lossless",
						"exportQuality": 0.8,
						"imageSpriteId": 2369782,
						"useCollisionPoly": true,
						"duration": 1,
						"tag": ""
					},
					{
						"width": 120,
						"height": 120,
						"originX": 0.5,
						"originY": 0.5,
						"originalSource": "",
						"exportFormat": "lossless",
						"exportQuality": 0.8,
						"imageSpriteId": 2531761,
						"useCollisionPoly": true,
						"duration": 1,
						"tag": ""
					}
				],
				"sid": 529308983604788,
				"name": "Active",
				"isLooping": true,
				"isPingPong": true,
				"repeatCount": 1,
				"repeatTo": 0,
				"speed": 5
			},
			{
				"frames": [
					{
						"width": 120,
						"height": 120,
						"originX": 0.5,
						"originY": 0.5,
						"originalSource": "",
						"exportFormat": "lossless",
						"exportQuality": 0.8,
						"imageSpriteId": 8857699,
						"useCollisionPoly": true,
						"duration": 1,
						"tag": ""
					},
					{
						"width": 120,
						"height": 120,
						"originX": 0.5,
						"originY": 0.5,
						"originalSource": "",
						"exportFormat": "lossless",
						"exportQuality": 0.8,
						"imageSpriteId": 3695430,
						"useCollisionPoly": true,
						"duration": 1,
						"tag": ""
					},
					{
						"width": 120,
						"height": 120,
						"originX": 0.5,
						"originY": 0.5,
						"originalSource": "",
						"exportFormat": "lossless",
						"exportQuality": 0.8,
						"imageSpriteId": 6561202,
						"useCollisionPoly": true,
						"duration": 1,
						"tag": ""
					},
					{
						"width": 120,
						"height": 120,
						"originX": 0.5,
						"originY": 0.5,
						"originalSource": "",
						"exportFormat": "lossless",
						"exportQuality": 0.8,
						"imageSpriteId": 1181338,
						"useCollisionPoly": true,
						"duration": 1,
						"tag": ""
					},
					{
						"width": 120,
						"height": 120,
						"originX": 0.5,
						"originY": 0.5,
						"originalSource": "",
						"exportFormat": "lossless",
						"exportQuality": 0.8,
						"imageSpriteId": 1580042,
						"useCollisionPoly": true,
						"duration": 1,
						"tag": ""
					},
					{
						"width": 120,
						"height": 120,
						"originX": 0.5,
						"originY": 0.5,
						"originalSource": "",
						"exportFormat": "lossless",
						"exportQuality": 0.8,
						"imageSpriteId": 7342139,
						"useCollisionPoly": true,
						"duration": 1,
						"tag": ""
					},
					{
						"width": 120,
						"height": 120,
						"originX": 0.5,
						"originY": 0.5,
						"originalSource": "",
						"exportFormat": "lossless",
						"exportQuality": 0.8,
						"imageSpriteId": 9626828,
						"useCollisionPoly": true,
						"duration": 1,
						"tag": ""
					}
				],
				"sid": 539395599517607,
				"name": "Overflow",
				"isLooping": false,
				"isPingPong": false,
				"repeatCount": 1,
				"repeatTo": 0,
				"speed": 5
			}
		],
		"subfolders": []
	}
}