{
	"name": "infoLayout_AT",
	"layers": [
		{
			"name": "Layer 0",
			"overriden": 0,
			"subLayers": [],
			"instances": [
				{
					"type": "temp_BG",
					"properties": {
						"initially-visible": true,
						"initial-animation": "Default",
						"initial-frame": 0,
						"enable-collisions": true,
						"live-preview": false
					},
					"uid": 848,
					"instanceVariables": {},
					"behaviors": {},
					"world": {
						"x": 960,
						"y": 539,
						"width": 1935.2857751354106,
						"height": 1096.7714650812463,
						"originX": 0.5,
						"originY": 0.5,
						"color": [
							1,
							1,
							1,
							1
						],
						"angle": 0,
						"zElevation": 0
					}
				},
				{
					"type": "CONTROLS",
					"properties": {
						"initially-visible": true,
						"initial-animation": "Default",
						"initial-frame": 0,
						"enable-collisions": true,
						"live-preview": false
					},
					"uid": 841,
					"instanceVariables": {},
					"behaviors": {},
					"world": {
						"x": 930,
						"y": 161,
						"width": 1096,
						"height": 272,
						"originX": 0.5,
						"originY": 0.5,
						"color": [
							1,
							1,
							1,
							1
						],
						"angle": 0,
						"zElevation": 0
					}
				},
				{
					"type": "back",
					"properties": {
						"initially-visible": true,
						"initial-animation": "Default",
						"initial-frame": 0,
						"enable-collisions": true,
						"live-preview": false
					},
					"uid": 842,
					"instanceVariables": {},
					"behaviors": {},
					"world": {
						"x": 1769,
						"y": 98,
						"width": 221,
						"height": 116,
						"originX": 0.5,
						"originY": 0.5,
						"color": [
							1,
							1,
							1,
							1
						],
						"angle": 0,
						"zElevation": 0
					}
				},
				{
					"type": "w",
					"properties": {
						"initially-visible": true,
						"initial-animation": "Default",
						"initial-frame": 0,
						"enable-collisions": true,
						"live-preview": false
					},
					"uid": 849,
					"instanceVariables": {},
					"behaviors": {},
					"world": {
						"x": 387,
						"y": 694,
						"width": 142.1962082453157,
						"height": 135.01458156625935,
						"originX": 0.5,
						"originY": 0.5,
						"color": [
							1,
							1,
							1,
							1
						],
						"angle": 0,
						"zElevation": 0
					}
				},
				{
					"type": "a",
					"properties": {
						"initially-visible": true,
						"initial-animation": "Default",
						"initial-frame": 0,
						"enable-collisions": true,
						"live-preview": false
					},
					"uid": 850,
					"instanceVariables": {},
					"behaviors": {},
					"world": {
						"x": 239,
						"y": 831,
						"width": 142.3520515537135,
						"height": 133.72465448985207,
						"originX": 0.5,
						"originY": 0.5,
						"color": [
							1,
							1,
							1,
							1
						],
						"angle": 0,
						"zElevation": 0
					}
				},
				{
					"type": "d",
					"properties": {
						"initially-visible": true,
						"initial-animation": "Default",
						"initial-frame": 0,
						"enable-collisions": true,
						"live-preview": false
					},
					"uid": 851,
					"instanceVariables": {},
					"behaviors": {},
					"world": {
						"x": 532,
						"y": 831,
						"width": 142.3520515537135,
						"height": 133.72465448985207,
						"originX": 0.5,
						"originY": 0.5,
						"color": [
							1,
							1,
							1,
							1
						],
						"angle": 0,
						"zElevation": 0
					}
				},
				{
					"type": "s",
					"properties": {
						"initially-visible": true,
						"initial-animation": "Default",
						"initial-frame": 0,
						"enable-collisions": true,
						"live-preview": false
					},
					"uid": 852,
					"instanceVariables": {},
					"behaviors": {},
					"world": {
						"x": 387,
						"y": 830,
						"width": 142.3520515537135,
						"height": 133.72465448985207,
						"originX": 0.5,
						"originY": 0.5,
						"color": [
							1,
							1,
							1,
							1
						],
						"angle": 0,
						"zElevation": 0
					}
				},
				{
					"type": "mouse2",
					"properties": {
						"initially-visible": true,
						"initial-animation": "Default",
						"initial-frame": 0,
						"enable-collisions": true,
						"live-preview": false
					},
					"uid": 854,
					"instanceVariables": {},
					"behaviors": {},
					"world": {
						"x": 986,
						"y": 763,
						"width": 171.67175745609663,
						"height": 270.7574698133068,
						"originX": 0.5,
						"originY": 0.5,
						"color": [
							1,
							1,
							1,
							1
						],
						"angle": 0,
						"zElevation": 0
					}
				},
				{
					"type": "E",
					"properties": {
						"initially-visible": true,
						"initial-animation": "Default",
						"initial-frame": 0,
						"enable-collisions": true,
						"live-preview": false
					},
					"uid": 855,
					"instanceVariables": {},
					"behaviors": {},
					"world": {
						"x": 1568,
						"y": 763,
						"width": 237.84809380174966,
						"height": 225.8355638117623,
						"originX": 0.5,
						"originY": 0.5,
						"color": [
							1,
							1,
							1,
							1
						],
						"angle": 0,
						"zElevation": 0
					}
				}
			],
			"sid": 547136302970407,
			"effectTypes": [],
			"isInitiallyVisible": true,
			"isInitiallyInteractive": true,
			"color": [
				1,
				1,
				1,
				1
			],
			"backgroundColor": [
				0.3686274509803922,
				0.3686274509803922,
				0.3686274509803922,
				1
			],
			"isTransparent": false,
			"parallaxX": 1,
			"parallaxY": 1,
			"scaleRate": 1,
			"forceOwnTexture": false,
			"renderingMode": "3d",
			"drawOrder": "z-order",
			"useRenderCells": false,
			"blendMode": "normal",
			"zElevation": 0,
			"global": false
		}
	],
	"sid": 353468498239967,
	"nonworld-instances": [],
	"effectTypes": [],
	"width": 3840,
	"height": 2160,
	"unboundedScrolling": false,
	"vpX": 0.5,
	"vpY": 0.5,
	"projection": "perspective",
	"eventSheet": "infoEvent_AT"
}